{
  "directed": false,
  "multigraph": false,
  "graph": {},
  "nodes": [
    {
      "label": "emergent.yml env image config",
      "file_type": "document",
      "source_file": ".emergent/emergent.yml",
      "source_location": null,
      "source_url": null,
      "captured_at": null,
      "author": null,
      "contributor": null,
      "community": 0,
      "norm_label": "emergent.yml env image config",
      "id": "emergent_emergent_emergent_emergent_emergent_emergent_emergent_emergent_emergent_emergent"
    },
    {
      "label": "CI workflow (build check)",
      "file_type": "document",
      "source_file": ".github/workflows/ci.yml",
      "source_location": null,
      "source_url": null,
      "captured_at": null,
      "author": null,
      "contributor": null,
      "community": 1,
      "norm_label": "ci workflow (build check)",
      "id": "github_workflows_ci"
    },
    {
      "label": "Send due reminders cron workflow",
      "file_type": "document",
      "source_file": ".github/workflows/cron-reminders.yml",
      "source_location": null,
      "source_url": null,
      "captured_at": null,
      "author": null,
      "contributor": null,
      "community": 2,
      "norm_label": "send due reminders cron workflow",
      "id": "github_workflows_cron_reminders"
    },
    {
      "label": "Deploy (Vercel) workflow",
      "file_type": "document",
      "source_file": ".github/workflows/deploy.yml",
      "source_location": null,
      "source_url": null,
      "captured_at": null,
      "author": null,
      "contributor": null,
      "community": 3,
      "norm_label": "deploy (vercel) workflow",
      "id": "github_workflows_deploy"
    },
    {
      "label": "E2E (Playwright) workflow",
      "file_type": "document",
      "source_file": ".github/workflows/e2e.yml",
      "source_location": null,
      "source_url": null,
      "captured_at": null,
      "author": null,
      "contributor": null,
      "community": 4,
      "norm_label": "e2e (playwright) workflow",
      "id": "github_workflows_e2e"
    },
    {
      "label": "Vercel Hobby plan daily-cron-only limitation",
      "file_type": "rationale",
      "source_file": ".github/workflows/cron-reminders.yml",
      "source_location": null,
      "source_url": null,
      "captured_at": null,
      "author": null,
      "contributor": null,
      "community": 2,
      "norm_label": "vercel hobby plan daily-cron-only limitation",
      "id": "github_workflows_cron_reminders_vercelhobbycronlimitation"
    }
  ],
  "links": [
    {
      "relation": "rationale_for",
      "confidence": "EXTRACTED",
      "confidence_score": 1.0,
      "source_file": ".github/workflows/cron-reminders.yml",
      "source_location": null,
      "weight": 1.0,
      "source": "github_workflows_cron_reminders_vercelhobbycronlimitation",
      "target": "github_workflows_cron_reminders"
    }
  ],
  "hyperedges": [],
  "built_at_commit": "1a540af1967dca1261d88806b7dc82a4474bdb31"
}